ai2/__init__.py
ai2/kubernetes/__init__.py
ai2/kubernetes/initializer/__init__.py
ai2/kubernetes/initializer/exceptions.py
ai2/kubernetes/initializer/initializer_controller.py
ai2/kubernetes/initializer/rejection.py
ai2/kubernetes/initializer/resource_controller.py
ai2/kubernetes/initializer/resource_handler.py
ai2/kubernetes/initializer/simple_resource_controller.py
ai2_kubernetes_initializer-0.1.0b4.dist-info/DESCRIPTION.rst
ai2_kubernetes_initializer-0.1.0b4.dist-info/METADATA
ai2_kubernetes_initializer-0.1.0b4.dist-info/RECORD
ai2_kubernetes_initializer-0.1.0b4.dist-info/WHEEL
ai2_kubernetes_initializer-0.1.0b4.dist-info/metadata.json
ai2_kubernetes_initializer-0.1.0b4.dist-info/top_level.txt
