Metadata-Version: 2.0
Name: ai2-kubernetes-initializer
Version: 0.1.0b4
Summary: A simple Kubernetes initializer library.
Home-page: https://github.com/allenai/kubernetes-initializer-python
Author: Jesse Kinkead
Author-email: jesse.kinkead@gmail.com
License: Apache License 2.0
Keywords: kubernetes initializer
Platform: UNKNOWN
Classifier: Development Status :: 4 - Beta
Classifier: Intended Audience :: Developers
Classifier: Topic :: Software Development :: Libraries
Classifier: Topic :: System :: Systems Administration
Classifier: License :: OSI Approved :: Apache Software License
Classifier: Programming Language :: Python :: 3
Classifier: Programming Language :: Python :: 3.6
Requires-Dist: kubernetes (>=3.0.0b1)
Requires-Dist: requests[security]
Requires-Dist: urllib3
